Metadata-Version: 1.2
Name: pyggtranslate
Version: 0.0.1
Summary: python translate by google
Home-page: https://github.com/lichv/pyggtranslate
Author: pyggtranslate
Author-email: lichvy@126.com
License: UNKNOWN
Platform: UNKNOWN
Requires-Python: >=3.6
